[
  {
    "player": "4Ply",
    "phases": [
      {
        "compRuns": 0,
        "pracRuns": 0,
        "totalRuns": 0,
        "tomesSubmitted": 0,
        "compWinRate": 0
      }
    ],
    "totalPracRuns": 0,
    "totalCompRuns": 0,
    "totalRunsAllModes": 0
  },
  {
    "player": "Amunja",
    "phases": [
      {
        "total": 1,
        "practice": {
          "total": 1,
          "easy": 0,
          "medium": 1,
          "hard": 0,
          "deadly": 0,
          "deepFrost": 0,
          "wins": 0,
          "losses": 1
        },
        "competitive": {
          "total": 0,
          "easy": 0,
          "medium": 0,
          "hard": 0,
          "deadly": 0,
          "deepFrost": 0,
          "wins": 0,
          "losses": 0
        },
        "tomesSubmitted": 0,
        "compRuns": 0,
        "pracRuns": 1,
        "totalRuns": 1,
        "compWinRate": 0
      }
    ],
    "totalPracRuns": 1,
    "totalCompRuns": 0,
    "totalRunsAllModes": 1
  },
  {
    "player": "Ariel_Gad",
    "phases": [
      {
        "total": 9,
        "practice": {
          "total": 9,
          "easy": 10,
          "medium": 0,
          "hard": 0,
          "deadly": 0,
          "deepFrost": 0,
          "wins": 2,
          "losses": 7
        },
        "competitive": {
          "total": 0,
          "easy": 0,
          "medium": 0,
          "hard": 0,
          "deadly": 0,
          "deepFrost": 0,
          "wins": 0,
          "losses": 0
        },
        "tomesSubmitted": 0,
        "compRuns": 0,
        "pracRuns": 9,
        "totalRuns": 9,
        "compWinRate": 0
      }
    ],
    "totalPracRuns": 9,
    "totalCompRuns": 0,
    "totalRunsAllModes": 9
  },
  {
    "player": "BroIsCookin",
    "phases": [
      {
        "total": 15,
        "practice": {
          "total": 15,
          "easy": 3,
          "medium": 8,
          "hard": 4,
          "deadly": 0,
          "deepFrost": 0,
          "wins": 8,
          "losses": 7
        },
        "competitive": {
          "total": 0,
          "easy": 0,
          "medium": 0,
          "hard": 0,
          "deadly": 0,
          "deepFrost": 0,
          "wins": 0,
          "losses": 0
        },
        "tomesSubmitted": 0,
        "compRuns": 0,
        "pracRuns": 15,
        "totalRuns": 15,
        "compWinRate": 0
      }
    ],
    "totalPracRuns": 15,
    "totalCompRuns": 0,
    "totalRunsAllModes": 15
  },
  {
    "player": "Cirrcinzo",
    "phases": [
      {
        "total": 4,
        "practice": {
          "total": 4,
          "easy": 0,
          "medium": 0,
          "hard": 2,
          "deadly": 2,
          "deepFrost": 0,
          "wins": 1,
          "losses": 3
        },
        "competitive": {
          "total": 0,
          "easy": 0,
          "medium": 0,
          "hard": 0,
          "deadly": 0,
          "deepFrost": 0,
          "wins": 0,
          "losses": 0
        },
        "tomesSubmitted": 0,
        "compRuns": 0,
        "pracRuns": 4,
        "totalRuns": 4,
        "compWinRate": 0
      }
    ],
    "totalPracRuns": 4,
    "totalCompRuns": 0,
    "totalRunsAllModes": 4
  },
  {
    "player": "CrazyEyedOldMan",
    "phases": [
      {
        "total": 34,
        "practice": {
          "total": 24,
          "easy": 12,
          "medium": 3,
          "hard": 5,
          "deadly": 3,
          "deepFrost": 1,
          "wins": 7,
          "losses": 17
        },
        "competitive": {
          "total": 10,
          "easy": 0,
          "medium": 8,
          "hard": 2,
          "deadly": 0,
          "deepFrost": 0,
          "wins": 4,
          "losses": 6
        },
        "tomesSubmitted": 0,
        "compRuns": 10,
        "pracRuns": 24,
        "totalRuns": 34,
        "compWinRate": 0.4
      }
    ],
    "totalPracRuns": 24,
    "totalCompRuns": 10,
    "totalRunsAllModes": 34
  },
  {
    "player": "Deepflea18",
    "phases": [
      {
        "total": 5,
        "practice": {
          "total": 5,
          "easy": 5,
          "medium": 0,
          "hard": 0,
          "deadly": 0,
          "deepFrost": 0,
          "wins": 2,
          "losses": 3
        },
        "competitive": {
          "total": 0,
          "easy": 0,
          "medium": 0,
          "hard": 0,
          "deadly": 0,
          "deepFrost": 0,
          "wins": 0,
          "losses": 0
        },
        "tomesSubmitted": 0,
        "compRuns": 0,
        "pracRuns": 5,
        "totalRuns": 5,
        "compWinRate": 0
      }
    ],
    "totalPracRuns": 5,
    "totalCompRuns": 0,
    "totalRunsAllModes": 5
  },
  {
    "player": "DiamondVortexX",
    "phases": [
      {
        "compRuns": 0,
        "pracRuns": 0,
        "totalRuns": 0,
        "tomesSubmitted": 0,
        "compWinRate": 0
      }
    ],
    "totalPracRuns": 0,
    "totalCompRuns": 0,
    "totalRunsAllModes": 0
  },
  {
    "player": "Dinosair",
    "phases": [
      {
        "total": 10,
        "practice": {
          "total": 0,
          "easy": 0,
          "medium": 0,
          "hard": 0,
          "deadly": 0,
          "deepFrost": 0,
          "wins": 0,
          "losses": 0
        },
        "competitive": {
          "total": 10,
          "easy": 0,
          "medium": 9,
          "hard": 1,
          "deadly": 0,
          "deepFrost": 0,
          "wins": 6,
          "losses": 4
        },
        "tomesSubmitted": 3,
        "compRuns": 10,
        "pracRuns": 0,
        "totalRuns": 10,
        "compWinRate": 0.6
      }
    ],
    "totalPracRuns": 0,
    "totalCompRuns": 10,
    "totalRunsAllModes": 10
  },
  {
    "player": "ErnieCarries",
    "phases": [
      {
        "total": 10,
        "practice": {
          "total": 0,
          "easy": 0,
          "medium": 0,
          "hard": 0,
          "deadly": 0,
          "deepFrost": 0,
          "wins": 0,
          "losses": 0
        },
        "competitive": {
          "total": 10,
          "easy": 1,
          "medium": 9,
          "hard": 0,
          "deadly": 0,
          "deepFrost": 0,
          "wins": 5,
          "losses": 5
        },
        "tomesSubmitted": 1,
        "compRuns": 10,
        "pracRuns": 0,
        "totalRuns": 10,
        "compWinRate": 0.5
      }
    ],
    "totalPracRuns": 0,
    "totalCompRuns": 10,
    "totalRunsAllModes": 10
  },
  {
    "player": "Ethereal_Ember_",
    "phases": [
      {
        "total": 10,
        "practice": {
          "total": 0,
          "easy": 0,
          "medium": 0,
          "hard": 0,
          "deadly": 0,
          "deepFrost": 0,
          "wins": 0,
          "losses": 0
        },
        "competitive": {
          "total": 10,
          "easy": 10,
          "medium": 0,
          "hard": 0,
          "deadly": 0,
          "deepFrost": 0,
          "wins": 4,
          "losses": 6
        },
        "tomesSubmitted": 1,
        "compRuns": 10,
        "pracRuns": 0,
        "totalRuns": 10,
        "compWinRate": 0.4
      }
    ],
    "totalPracRuns": 0,
    "totalCompRuns": 10,
    "totalRunsAllModes": 10
  },
  {
    "player": "FatedforNewTroy",
    "phases": [
      {
        "total": 62,
        "practice": {
          "total": 61,
          "easy": 60,
          "medium": 1,
          "hard": 0,
          "deadly": 0,
          "deepFrost": 0,
          "wins": 38,
          "losses": 23
        },
        "competitive": {
          "total": 1,
          "easy": 1,
          "medium": 0,
          "hard": 0,
          "deadly": 0,
          "deepFrost": 0,
          "wins": 1,
          "losses": 0
        },
        "tomesSubmitted": 0,
        "compRuns": 1,
        "pracRuns": 61,
        "totalRuns": 62,
        "compWinRate": 1
      }
    ],
    "totalPracRuns": 61,
    "totalCompRuns": 1,
    "totalRunsAllModes": 62
  },
  {
    "player": "FinnyMarigold58",
    "phases": [
      {
        "compRuns": 0,
        "pracRuns": 0,
        "totalRuns": 0,
        "tomesSubmitted": 0,
        "compWinRate": 0
      }
    ],
    "totalPracRuns": 0,
    "totalCompRuns": 0,
    "totalRunsAllModes": 0
  },
  {
    "player": "FruitFalls",
    "phases": [
      {
        "total": 14,
        "practice": {
          "total": 3,
          "easy": 0,
          "medium": 0,
          "hard": 0,
          "deadly": 1,
          "deepFrost": 3,
          "wins": 1,
          "losses": 2
        },
        "competitive": {
          "total": 11,
          "easy": 8,
          "medium": 1,
          "hard": 2,
          "deadly": 0,
          "deepFrost": 0,
          "wins": 5,
          "losses": 6
        },
        "tomesSubmitted": 0,
        "compRuns": 11,
        "pracRuns": 3,
        "totalRuns": 14,
        "compWinRate": 0.45454545454545453
      }
    ],
    "totalPracRuns": 3,
    "totalCompRuns": 11,
    "totalRunsAllModes": 14
  },
  {
    "player": "FrustratedCPU",
    "phases": [
      {
        "total": 5,
        "practice": {
          "total": 0,
          "easy": 0,
          "medium": 0,
          "hard": 0,
          "deadly": 0,
          "deepFrost": 0,
          "wins": 0,
          "losses": 0
        },
        "competitive": {
          "total": 5,
          "easy": 0,
          "medium": 5,
          "hard": 0,
          "deadly": 0,
          "deepFrost": 0,
          "wins": 3,
          "losses": 2
        },
        "tomesSubmitted": 0,
        "compRuns": 5,
        "pracRuns": 0,
        "totalRuns": 5,
        "compWinRate": 0.6
      }
    ],
    "totalPracRuns": 0,
    "totalCompRuns": 5,
    "totalRunsAllModes": 5
  },
  {
    "player": "Great_The_Cait",
    "phases": [
      {
        "total": 12,
        "practice": {
          "total": 2,
          "easy": 0,
          "medium": 0,
          "hard": 2,
          "deadly": 0,
          "deepFrost": 0,
          "wins": 0,
          "losses": 2
        },
        "competitive": {
          "total": 10,
          "easy": 0,
          "medium": 10,
          "hard": 1,
          "deadly": 0,
          "deepFrost": 0,
          "wins": 3,
          "losses": 7
        },
        "tomesSubmitted": 0,
        "compRuns": 10,
        "pracRuns": 2,
        "totalRuns": 12,
        "compWinRate": 0.3
      }
    ],
    "totalPracRuns": 2,
    "totalCompRuns": 10,
    "totalRunsAllModes": 12
  },
  {
    "player": "HonningBjornen",
    "phases": [
      {
        "total": 8,
        "practice": {
          "total": 0,
          "easy": 0,
          "medium": 0,
          "hard": 0,
          "deadly": 0,
          "deepFrost": 0,
          "wins": 0,
          "losses": 0
        },
        "competitive": {
          "total": 8,
          "easy": 8,
          "medium": 0,
          "hard": 0,
          "deadly": 0,
          "deepFrost": 0,
          "wins": 2,
          "losses": 6
        },
        "tomesSubmitted": 0,
        "compRuns": 8,
        "pracRuns": 0,
        "totalRuns": 8,
        "compWinRate": 0.25
      }
    ],
    "totalPracRuns": 0,
    "totalCompRuns": 8,
    "totalRunsAllModes": 8
  },
  {
    "player": "Iceberg3436",
    "phases": [
      {
        "compRuns": 0,
        "pracRuns": 0,
        "totalRuns": 0,
        "tomesSubmitted": 0,
        "compWinRate": 0
      }
    ],
    "totalPracRuns": 0,
    "totalCompRuns": 0,
    "totalRunsAllModes": 0
  },
  {
    "player": "InaByt",
    "phases": [
      {
        "total": 10,
        "practice": {
          "total": 0,
          "easy": 0,
          "medium": 0,
          "hard": 0,
          "deadly": 0,
          "deepFrost": 0,
          "wins": 0,
          "losses": 0
        },
        "competitive": {
          "total": 10,
          "easy": 3,
          "medium": 7,
          "hard": 0,
          "deadly": 0,
          "deepFrost": 0,
          "wins": 6,
          "losses": 4
        },
        "tomesSubmitted": 0,
        "compRuns": 10,
        "pracRuns": 0,
        "totalRuns": 10,
        "compWinRate": 0.6
      }
    ],
    "totalPracRuns": 0,
    "totalCompRuns": 10,
    "totalRunsAllModes": 10
  },
  {
    "player": "JTRex1",
    "phases": [
      {
        "total": 1,
        "practice": {
          "total": 1,
          "easy": 1,
          "medium": 0,
          "hard": 0,
          "deadly": 0,
          "deepFrost": 0,
          "wins": 0,
          "losses": 1
        },
        "competitive": {
          "total": 0,
          "easy": 0,
          "medium": 0,
          "hard": 0,
          "deadly": 0,
          "deepFrost": 0,
          "wins": 0,
          "losses": 0
        },
        "tomesSubmitted": 0,
        "compRuns": 0,
        "pracRuns": 1,
        "totalRuns": 1,
        "compWinRate": 0
      }
    ],
    "totalPracRuns": 1,
    "totalCompRuns": 0,
    "totalRunsAllModes": 1
  },
  {
    "player": "Jaymac720",
    "phases": [
      {
        "total": 4,
        "practice": {
          "total": 3,
          "easy": 3,
          "medium": 0,
          "hard": 0,
          "deadly": 0,
          "deepFrost": 0,
          "wins": 2,
          "losses": 1
        },
        "competitive": {
          "total": 1,
          "easy": 1,
          "medium": 0,
          "hard": 0,
          "deadly": 0,
          "deepFrost": 0,
          "wins": 1,
          "losses": 0
        },
        "tomesSubmitted": 0,
        "compRuns": 1,
        "pracRuns": 3,
        "totalRuns": 4,
        "compWinRate": 1
      }
    ],
    "totalPracRuns": 3,
    "totalCompRuns": 1,
    "totalRunsAllModes": 4
  },
  {
    "player": "Ketoxica",
    "phases": [
      {
        "total": 2,
        "practice": {
          "total": 2,
          "easy": 1,
          "medium": 0,
          "hard": 1,
          "deadly": 0,
          "deepFrost": 0,
          "wins": 0,
          "losses": 2
        },
        "competitive": {
          "total": 0,
          "easy": 0,
          "medium": 0,
          "hard": 0,
          "deadly": 0,
          "deepFrost": 0,
          "wins": 0,
          "losses": 0
        },
        "tomesSubmitted": 0,
        "compRuns": 0,
        "pracRuns": 2,
        "totalRuns": 2,
        "compWinRate": 0
      }
    ],
    "totalPracRuns": 2,
    "totalCompRuns": 0,
    "totalRunsAllModes": 2
  },
  {
    "player": "KnightMiner77",
    "phases": [
      {
        "total": 8,
        "practice": {
          "total": 8,
          "easy": 0,
          "medium": 7,
          "hard": 1,
          "deadly": 0,
          "deepFrost": 0,
          "wins": 6,
          "losses": 2
        },
        "competitive": {
          "total": 0,
          "easy": 0,
          "medium": 0,
          "hard": 0,
          "deadly": 0,
          "deepFrost": 0,
          "wins": 0,
          "losses": 0
        },
        "tomesSubmitted": 0,
        "compRuns": 0,
        "pracRuns": 8,
        "totalRuns": 8,
        "compWinRate": 0
      }
    ],
    "totalPracRuns": 8,
    "totalCompRuns": 0,
    "totalRunsAllModes": 8
  },
  {
    "player": "Kraxy19",
    "phases": [
      {
        "total": 17,
        "practice": {
          "total": 7,
          "easy": 0,
          "medium": 0,
          "hard": 6,
          "deadly": 1,
          "deepFrost": 0,
          "wins": 3,
          "losses": 4
        },
        "competitive": {
          "total": 10,
          "easy": 1,
          "medium": 9,
          "hard": 0,
          "deadly": 0,
          "deepFrost": 0,
          "wins": 7,
          "losses": 3
        },
        "tomesSubmitted": 0,
        "compRuns": 10,
        "pracRuns": 7,
        "totalRuns": 17,
        "compWinRate": 0.7
      }
    ],
    "totalPracRuns": 7,
    "totalCompRuns": 10,
    "totalRunsAllModes": 17
  },
  {
    "player": "KuzcoTheDog",
    "phases": [
      {
        "total": 10,
        "practice": {
          "total": 5,
          "easy": 4,
          "medium": 1,
          "hard": 0,
          "deadly": 0,
          "deepFrost": 0,
          "wins": 2,
          "losses": 3
        },
        "competitive": {
          "total": 5,
          "easy": 0,
          "medium": 5,
          "hard": 0,
          "deadly": 0,
          "deepFrost": 0,
          "wins": 3,
          "losses": 2
        },
        "tomesSubmitted": 0,
        "compRuns": 5,
        "pracRuns": 5,
        "totalRuns": 10,
        "compWinRate": 0.6
      }
    ],
    "totalPracRuns": 5,
    "totalCompRuns": 5,
    "totalRunsAllModes": 10
  },
  {
    "player": "Lanrick2002",
    "phases": [
      {
        "compRuns": 0,
        "pracRuns": 0,
        "totalRuns": 0,
        "tomesSubmitted": 0,
        "compWinRate": 0
      }
    ],
    "totalPracRuns": 0,
    "totalCompRuns": 0,
    "totalRunsAllModes": 0
  },
  {
    "player": "MaplestoryAran",
    "phases": [
      {
        "total": 3,
        "practice": {
          "total": 1,
          "easy": 0,
          "medium": 0,
          "hard": 1,
          "deadly": 0,
          "deepFrost": 0,
          "wins": 0,
          "losses": 1
        },
        "competitive": {
          "total": 2,
          "easy": 2,
          "medium": 0,
          "hard": 0,
          "deadly": 0,
          "deepFrost": 0,
          "wins": 1,
          "losses": 1
        },
        "tomesSubmitted": 0,
        "compRuns": 2,
        "pracRuns": 1,
        "totalRuns": 3,
        "compWinRate": 0.5
      }
    ],
    "totalPracRuns": 1,
    "totalCompRuns": 2,
    "totalRunsAllModes": 3
  },
  {
    "player": "Mariozet",
    "phases": [
      {
        "total": 40,
        "practice": {
          "total": 30,
          "easy": 0,
          "medium": 0,
          "hard": 30,
          "deadly": 0,
          "deepFrost": 0,
          "wins": 6,
          "losses": 24
        },
        "competitive": {
          "total": 10,
          "easy": 0,
          "medium": 7,
          "hard": 3,
          "deadly": 0,
          "deepFrost": 0,
          "wins": 4,
          "losses": 6
        },
        "tomesSubmitted": 3,
        "compRuns": 10,
        "pracRuns": 30,
        "totalRuns": 40,
        "compWinRate": 0.4
      }
    ],
    "totalPracRuns": 30,
    "totalCompRuns": 10,
    "totalRunsAllModes": 40
  },
  {
    "player": "Moosiq",
    "phases": [
      {
        "total": 10,
        "practice": {
          "total": 0,
          "easy": 0,
          "medium": 0,
          "hard": 0,
          "deadly": 0,
          "deepFrost": 0,
          "wins": 0,
          "losses": 0
        },
        "competitive": {
          "total": 10,
          "easy": 1,
          "medium": 9,
          "hard": 0,
          "deadly": 0,
          "deepFrost": 0,
          "wins": 8,
          "losses": 2
        },
        "tomesSubmitted": 2,
        "compRuns": 10,
        "pracRuns": 0,
        "totalRuns": 10,
        "compWinRate": 0.8
      }
    ],
    "totalPracRuns": 0,
    "totalCompRuns": 10,
    "totalRunsAllModes": 10
  },
  {
    "player": "MrFireflyer",
    "phases": [
      {
        "total": 10,
        "practice": {
          "total": 0,
          "easy": 0,
          "medium": 0,
          "hard": 0,
          "deadly": 0,
          "deepFrost": 0,
          "wins": 0,
          "losses": 0
        },
        "competitive": {
          "total": 10,
          "easy": 2,
          "medium": 8,
          "hard": 0,
          "deadly": 0,
          "deepFrost": 0,
          "wins": 8,
          "losses": 2
        },
        "tomesSubmitted": 1,
        "compRuns": 10,
        "pracRuns": 0,
        "totalRuns": 10,
        "compWinRate": 0.8
      }
    ],
    "totalPracRuns": 0,
    "totalCompRuns": 10,
    "totalRunsAllModes": 10
  },
  {
    "player": "MythicalCucumber",
    "phases": [
      {
        "total": 4,
        "practice": {
          "total": 4,
          "easy": 0,
          "medium": 2,
          "hard": 2,
          "deadly": 0,
          "deepFrost": 0,
          "wins": 1,
          "losses": 3
        },
        "competitive": {
          "total": 0,
          "easy": 0,
          "medium": 0,
          "hard": 0,
          "deadly": 0,
          "deepFrost": 0,
          "wins": 0,
          "losses": 0
        },
        "tomesSubmitted": 0,
        "compRuns": 0,
        "pracRuns": 4,
        "totalRuns": 4,
        "compWinRate": 0
      }
    ],
    "totalPracRuns": 4,
    "totalCompRuns": 0,
    "totalRunsAllModes": 4
  },
  {
    "player": "NethereseHat",
    "phases": [
      {
        "total": 22,
        "practice": {
          "total": 22,
          "easy": 10,
          "medium": 14,
          "hard": 0,
          "deadly": 0,
          "deepFrost": 0,
          "wins": 7,
          "losses": 15
        },
        "competitive": {
          "total": 0,
          "easy": 0,
          "medium": 0,
          "hard": 0,
          "deadly": 0,
          "deepFrost": 0,
          "wins": 0,
          "losses": 0
        },
        "tomesSubmitted": 0,
        "compRuns": 0,
        "pracRuns": 22,
        "totalRuns": 22,
        "compWinRate": 0
      }
    ],
    "totalPracRuns": 22,
    "totalCompRuns": 0,
    "totalRunsAllModes": 22
  },
  {
    "player": "OpaJones",
    "phases": [
      {
        "total": 20,
        "practice": {
          "total": 10,
          "easy": 5,
          "medium": 4,
          "hard": 0,
          "deadly": 0,
          "deepFrost": 1,
          "wins": 5,
          "losses": 5
        },
        "competitive": {
          "total": 10,
          "easy": 3,
          "medium": 7,
          "hard": 0,
          "deadly": 0,
          "deepFrost": 0,
          "wins": 6,
          "losses": 4
        },
        "tomesSubmitted": 2,
        "compRuns": 10,
        "pracRuns": 10,
        "totalRuns": 20,
        "compWinRate": 0.6
      }
    ],
    "totalPracRuns": 10,
    "totalCompRuns": 10,
    "totalRunsAllModes": 20
  },
  {
    "player": "PeakGalaxy73634",
    "phases": [
      {
        "total": 12,
        "practice": {
          "total": 2,
          "easy": 0,
          "medium": 2,
          "hard": 0,
          "deadly": 0,
          "deepFrost": 0,
          "wins": 2,
          "losses": 0
        },
        "competitive": {
          "total": 10,
          "easy": 5,
          "medium": 5,
          "hard": 0,
          "deadly": 0,
          "deepFrost": 0,
          "wins": 5,
          "losses": 5
        },
        "tomesSubmitted": 1,
        "compRuns": 10,
        "pracRuns": 2,
        "totalRuns": 12,
        "compWinRate": 0.5
      }
    ],
    "totalPracRuns": 2,
    "totalCompRuns": 10,
    "totalRunsAllModes": 12
  },
  {
    "player": "R_M2468",
    "phases": [
      {
        "total": 10,
        "practice": {
          "total": 0,
          "easy": 0,
          "medium": 0,
          "hard": 0,
          "deadly": 0,
          "deepFrost": 0,
          "wins": 0,
          "losses": 0
        },
        "competitive": {
          "total": 10,
          "easy": 4,
          "medium": 5,
          "hard": 1,
          "deadly": 0,
          "deepFrost": 0,
          "wins": 6,
          "losses": 4
        },
        "tomesSubmitted": 1,
        "compRuns": 10,
        "pracRuns": 0,
        "totalRuns": 10,
        "compWinRate": 0.6
      }
    ],
    "totalPracRuns": 0,
    "totalCompRuns": 10,
    "totalRunsAllModes": 10
  },
  {
    "player": "Rawrdardian",
    "phases": [
      {
        "total": 18,
        "practice": {
          "total": 8,
          "easy": 0,
          "medium": 1,
          "hard": 1,
          "deadly": 0,
          "deepFrost": 3,
          "wins": 1,
          "losses": 7
        },
        "competitive": {
          "total": 10,
          "easy": 1,
          "medium": 8,
          "hard": 1,
          "deadly": 0,
          "deepFrost": 0,
          "wins": 7,
          "losses": 3
        },
        "tomesSubmitted": 1,
        "compRuns": 10,
        "pracRuns": 8,
        "totalRuns": 18,
        "compWinRate": 0.7
      }
    ],
    "totalPracRuns": 8,
    "totalCompRuns": 10,
    "totalRunsAllModes": 18
  },
  {
    "player": "RealPokeplaya",
    "phases": [
      {
        "total": 8,
        "practice": {
          "total": 8,
          "easy": 8,
          "medium": 0,
          "hard": 0,
          "deadly": 0,
          "deepFrost": 0,
          "wins": 2,
          "losses": 6
        },
        "competitive": {
          "total": 0,
          "easy": 0,
          "medium": 0,
          "hard": 0,
          "deadly": 0,
          "deepFrost": 0,
          "wins": 0,
          "losses": 0
        },
        "tomesSubmitted": 0,
        "compRuns": 0,
        "pracRuns": 8,
        "totalRuns": 8,
        "compWinRate": 0
      }
    ],
    "totalPracRuns": 8,
    "totalCompRuns": 0,
    "totalRunsAllModes": 8
  },
  {
    "player": "Reborned",
    "phases": [
      {
        "compRuns": 0,
        "pracRuns": 0,
        "totalRuns": 0,
        "tomesSubmitted": 0,
        "compWinRate": 0
      }
    ],
    "totalPracRuns": 0,
    "totalCompRuns": 0,
    "totalRunsAllModes": 0
  },
  {
    "player": "Sculk_Sensor",
    "phases": [
      {
        "compRuns": 0,
        "pracRuns": 0,
        "totalRuns": 0,
        "tomesSubmitted": 0,
        "compWinRate": 0
      }
    ],
    "totalPracRuns": 0,
    "totalCompRuns": 0,
    "totalRunsAllModes": 0
  },
  {
    "player": "Shockwave13",
    "phases": [
      {
        "total": 12,
        "practice": {
          "total": 2,
          "easy": 0,
          "medium": 0,
          "hard": 2,
          "deadly": 0,
          "deepFrost": 0,
          "wins": 0,
          "losses": 2
        },
        "competitive": {
          "total": 10,
          "easy": 1,
          "medium": 9,
          "hard": 0,
          "deadly": 0,
          "deepFrost": 0,
          "wins": 7,
          "losses": 3
        },
        "tomesSubmitted": 1,
        "compRuns": 10,
        "pracRuns": 2,
        "totalRuns": 12,
        "compWinRate": 0.7
      }
    ],
    "totalPracRuns": 2,
    "totalCompRuns": 10,
    "totalRunsAllModes": 12
  },
  {
    "player": "Shorju",
    "phases": [
      {
        "total": 44,
        "practice": {
          "total": 34,
          "easy": 5,
          "medium": 14,
          "hard": 15,
          "deadly": 0,
          "deepFrost": 0,
          "wins": 9,
          "losses": 25
        },
        "competitive": {
          "total": 10,
          "easy": 1,
          "medium": 9,
          "hard": 0,
          "deadly": 0,
          "deepFrost": 0,
          "wins": 5,
          "losses": 5
        },
        "tomesSubmitted": 1,
        "compRuns": 10,
        "pracRuns": 34,
        "totalRuns": 44,
        "compWinRate": 0.5
      }
    ],
    "totalPracRuns": 34,
    "totalCompRuns": 10,
    "totalRunsAllModes": 44
  },
  {
    "player": "SilverPhantom07",
    "phases": [
      {
        "total": 10,
        "practice": {
          "total": 0,
          "easy": 0,
          "medium": 0,
          "hard": 0,
          "deadly": 0,
          "deepFrost": 0,
          "wins": 0,
          "losses": 0
        },
        "competitive": {
          "total": 10,
          "easy": 6,
          "medium": 4,
          "hard": 0,
          "deadly": 0,
          "deepFrost": 0,
          "wins": 8,
          "losses": 2
        },
        "tomesSubmitted": 0,
        "compRuns": 10,
        "pracRuns": 0,
        "totalRuns": 10,
        "compWinRate": 0.8
      }
    ],
    "totalPracRuns": 0,
    "totalCompRuns": 10,
    "totalRunsAllModes": 10
  },
  {
    "player": "Sleepy_Auri",
    "phases": [
      {
        "total": 11,
        "practice": {
          "total": 1,
          "easy": 0,
          "medium": 1,
          "hard": 0,
          "deadly": 0,
          "deepFrost": 0,
          "wins": 1,
          "losses": 0
        },
        "competitive": {
          "total": 10,
          "easy": 8,
          "medium": 2,
          "hard": 0,
          "deadly": 0,
          "deepFrost": 0,
          "wins": 4,
          "losses": 6
        },
        "tomesSubmitted": 0,
        "compRuns": 10,
        "pracRuns": 1,
        "totalRuns": 11,
        "compWinRate": 0.4
      }
    ],
    "totalPracRuns": 1,
    "totalCompRuns": 10,
    "totalRunsAllModes": 11
  },
  {
    "player": "Space4nd",
    "phases": [
      {
        "total": 10,
        "practice": {
          "total": 10,
          "easy": 3,
          "medium": 7,
          "hard": 0,
          "deadly": 0,
          "deepFrost": 0,
          "wins": 2,
          "losses": 8
        },
        "competitive": {
          "total": 0,
          "easy": 0,
          "medium": 0,
          "hard": 0,
          "deadly": 0,
          "deepFrost": 0,
          "wins": 0,
          "losses": 0
        },
        "tomesSubmitted": 0,
        "compRuns": 0,
        "pracRuns": 10,
        "totalRuns": 10,
        "compWinRate": 0
      }
    ],
    "totalPracRuns": 10,
    "totalCompRuns": 0,
    "totalRunsAllModes": 10
  },
  {
    "player": "Starwarschamp4",
    "phases": [
      {
        "total": 5,
        "practice": {
          "total": 4,
          "easy": 2,
          "medium": 2,
          "hard": 0,
          "deadly": 0,
          "deepFrost": 0,
          "wins": 1,
          "losses": 3
        },
        "competitive": {
          "total": 1,
          "easy": 0,
          "medium": 1,
          "hard": 0,
          "deadly": 0,
          "deepFrost": 0,
          "wins": 0,
          "losses": 1
        },
        "tomesSubmitted": 0,
        "compRuns": 1,
        "pracRuns": 4,
        "totalRuns": 5,
        "compWinRate": 0
      }
    ],
    "totalPracRuns": 4,
    "totalCompRuns": 1,
    "totalRunsAllModes": 5
  },
  {
    "player": "StratoBlast74",
    "phases": [
      {
        "total": 11,
        "practice": {
          "total": 0,
          "easy": 0,
          "medium": 0,
          "hard": 0,
          "deadly": 0,
          "deepFrost": 0,
          "wins": 0,
          "losses": 0
        },
        "competitive": {
          "total": 11,
          "easy": 7,
          "medium": 4,
          "hard": 0,
          "deadly": 0,
          "deepFrost": 0,
          "wins": 8,
          "losses": 3
        },
        "tomesSubmitted": 2,
        "compRuns": 11,
        "pracRuns": 0,
        "totalRuns": 11,
        "compWinRate": 0.7272727272727273
      }
    ],
    "totalPracRuns": 0,
    "totalCompRuns": 11,
    "totalRunsAllModes": 11
  },
  {
    "player": "TangerineTrip",
    "phases": [
      {
        "total": 10,
        "practice": {
          "total": 0,
          "easy": 0,
          "medium": 0,
          "hard": 0,
          "deadly": 0,
          "deepFrost": 0,
          "wins": 0,
          "losses": 0
        },
        "competitive": {
          "total": 10,
          "easy": 5,
          "medium": 4,
          "hard": 1,
          "deadly": 0,
          "deepFrost": 0,
          "wins": 5,
          "losses": 5
        },
        "tomesSubmitted": 0,
        "compRuns": 10,
        "pracRuns": 0,
        "totalRuns": 10,
        "compWinRate": 0.5
      }
    ],
    "totalPracRuns": 0,
    "totalCompRuns": 10,
    "totalRunsAllModes": 10
  },
  {
    "player": "TempestJayKo",
    "phases": [
      {
        "compRuns": 0,
        "pracRuns": 0,
        "totalRuns": 0,
        "tomesSubmitted": 0,
        "compWinRate": 0
      }
    ],
    "totalPracRuns": 0,
    "totalCompRuns": 0,
    "totalRunsAllModes": 0
  },
  {
    "player": "TheRedBladess",
    "phases": [
      {
        "total": 10,
        "practice": {
          "total": 0,
          "easy": 0,
          "medium": 0,
          "hard": 0,
          "deadly": 0,
          "deepFrost": 0,
          "wins": 0,
          "losses": 0
        },
        "competitive": {
          "total": 10,
          "easy": 9,
          "medium": 1,
          "hard": 0,
          "deadly": 0,
          "deepFrost": 0,
          "wins": 7,
          "losses": 3
        },
        "tomesSubmitted": 0,
        "compRuns": 10,
        "pracRuns": 0,
        "totalRuns": 10,
        "compWinRate": 0.7
      }
    ],
    "totalPracRuns": 0,
    "totalCompRuns": 10,
    "totalRunsAllModes": 10
  },
  {
    "player": "The_Kings_Wit_",
    "phases": [
      {
        "total": 8,
        "practice": {
          "total": 4,
          "easy": 1,
          "medium": 0,
          "hard": 1,
          "deadly": 1,
          "deepFrost": 1,
          "wins": 2,
          "losses": 2
        },
        "competitive": {
          "total": 4,
          "easy": 3,
          "medium": 1,
          "hard": 0,
          "deadly": 0,
          "deepFrost": 0,
          "wins": 3,
          "losses": 1
        },
        "tomesSubmitted": 1,
        "compRuns": 4,
        "pracRuns": 4,
        "totalRuns": 8,
        "compWinRate": 0.75
      }
    ],
    "totalPracRuns": 4,
    "totalCompRuns": 4,
    "totalRunsAllModes": 8
  },
  {
    "player": "Tostero",
    "phases": [
      {
        "total": 34,
        "practice": {
          "total": 24,
          "easy": 0,
          "medium": 0,
          "hard": 24,
          "deadly": 0,
          "deepFrost": 0,
          "wins": 4,
          "losses": 20
        },
        "competitive": {
          "total": 10,
          "easy": 1,
          "medium": 9,
          "hard": 0,
          "deadly": 0,
          "deepFrost": 0,
          "wins": 8,
          "losses": 2
        },
        "tomesSubmitted": 5,
        "compRuns": 10,
        "pracRuns": 24,
        "totalRuns": 34,
        "compWinRate": 0.8
      }
    ],
    "totalPracRuns": 24,
    "totalCompRuns": 10,
    "totalRunsAllModes": 34
  },
  {
    "player": "VincentTheVifth",
    "phases": [
      {
        "total": 6,
        "practice": {
          "total": 0,
          "easy": 0,
          "medium": 0,
          "hard": 0,
          "deadly": 0,
          "deepFrost": 0,
          "wins": 0,
          "losses": 0
        },
        "competitive": {
          "total": 6,
          "easy": 3,
          "medium": 3,
          "hard": 0,
          "deadly": 0,
          "deepFrost": 0,
          "wins": 4,
          "losses": 2
        },
        "tomesSubmitted": 0,
        "compRuns": 6,
        "pracRuns": 0,
        "totalRuns": 6,
        "compWinRate": 0.6666666666666666
      }
    ],
    "totalPracRuns": 0,
    "totalCompRuns": 6,
    "totalRunsAllModes": 6
  },
  {
    "player": "Wiczki",
    "phases": [
      {
        "total": 15,
        "practice": {
          "total": 6,
          "easy": 1,
          "medium": 3,
          "hard": 0,
          "deadly": 0,
          "deepFrost": 0,
          "wins": 2,
          "losses": 4
        },
        "competitive": {
          "total": 9,
          "easy": 10,
          "medium": 0,
          "hard": 0,
          "deadly": 0,
          "deepFrost": 0,
          "wins": 3,
          "losses": 6
        },
        "tomesSubmitted": 2,
        "compRuns": 9,
        "pracRuns": 6,
        "totalRuns": 15,
        "compWinRate": 0.3333333333333333
      }
    ],
    "totalPracRuns": 6,
    "totalCompRuns": 9,
    "totalRunsAllModes": 15
  },
  {
    "player": "Wumpleberries",
    "phases": [
      {
        "total": 56,
        "practice": {
          "total": 46,
          "easy": 0,
          "medium": 14,
          "hard": 32,
          "deadly": 0,
          "deepFrost": 0,
          "wins": 10,
          "losses": 36
        },
        "competitive": {
          "total": 10,
          "easy": 4,
          "medium": 6,
          "hard": 0,
          "deadly": 0,
          "deepFrost": 0,
          "wins": 4,
          "losses": 6
        },
        "tomesSubmitted": 0,
        "compRuns": 10,
        "pracRuns": 46,
        "totalRuns": 56,
        "compWinRate": 0.4
      }
    ],
    "totalPracRuns": 46,
    "totalCompRuns": 10,
    "totalRunsAllModes": 56
  },
  {
    "player": "YellowDuckKing4",
    "phases": [
      {
        "compRuns": 0,
        "pracRuns": 0,
        "totalRuns": 0,
        "tomesSubmitted": 0,
        "compWinRate": 0
      }
    ],
    "totalPracRuns": 0,
    "totalCompRuns": 0,
    "totalRunsAllModes": 0
  },
  {
    "player": "brimborium",
    "phases": [
      {
        "total": 10,
        "practice": {
          "total": 0,
          "easy": 0,
          "medium": 0,
          "hard": 0,
          "deadly": 0,
          "deepFrost": 0,
          "wins": 0,
          "losses": 0
        },
        "competitive": {
          "total": 10,
          "easy": 10,
          "medium": 0,
          "hard": 0,
          "deadly": 0,
          "deepFrost": 0,
          "wins": 6,
          "losses": 4
        },
        "tomesSubmitted": 1,
        "compRuns": 10,
        "pracRuns": 0,
        "totalRuns": 10,
        "compWinRate": 0.6
      }
    ],
    "totalPracRuns": 0,
    "totalCompRuns": 10,
    "totalRunsAllModes": 10
  },
  {
    "player": "busta8",
    "phases": [
      {
        "total": 36,
        "practice": {
          "total": 36,
          "easy": 16,
          "medium": 16,
          "hard": 4,
          "deadly": 0,
          "deepFrost": 0,
          "wins": 17,
          "losses": 19
        },
        "competitive": {
          "total": 0,
          "easy": 0,
          "medium": 0,
          "hard": 0,
          "deadly": 0,
          "deepFrost": 0,
          "wins": 0,
          "losses": 0
        },
        "tomesSubmitted": 0,
        "compRuns": 0,
        "pracRuns": 36,
        "totalRuns": 36,
        "compWinRate": 0
      }
    ],
    "totalPracRuns": 36,
    "totalCompRuns": 0,
    "totalRunsAllModes": 36
  },
  {
    "player": "codacorgi",
    "phases": [
      {
        "total": 13,
        "practice": {
          "total": 13,
          "easy": 0,
          "medium": 13,
          "hard": 0,
          "deadly": 0,
          "deepFrost": 0,
          "wins": 1,
          "losses": 12
        },
        "competitive": {
          "total": 0,
          "easy": 0,
          "medium": 0,
          "hard": 0,
          "deadly": 0,
          "deepFrost": 0,
          "wins": 0,
          "losses": 0
        },
        "tomesSubmitted": 0,
        "compRuns": 0,
        "pracRuns": 13,
        "totalRuns": 13,
        "compWinRate": 0
      }
    ],
    "totalPracRuns": 13,
    "totalCompRuns": 0,
    "totalRunsAllModes": 13
  },
  {
    "player": "feyuwu",
    "phases": [
      {
        "compRuns": 0,
        "pracRuns": 0,
        "totalRuns": 0,
        "tomesSubmitted": 0,
        "compWinRate": 0
      }
    ],
    "totalPracRuns": 0,
    "totalCompRuns": 0,
    "totalRunsAllModes": 0
  },
  {
    "player": "jaek95",
    "phases": [
      {
        "compRuns": 0,
        "pracRuns": 0,
        "totalRuns": 0,
        "tomesSubmitted": 0,
        "compWinRate": 0
      }
    ],
    "totalPracRuns": 0,
    "totalCompRuns": 0,
    "totalRunsAllModes": 0
  },
  {
    "player": "pepperoni365",
    "phases": [
      {
        "total": 10,
        "practice": {
          "total": 0,
          "easy": 0,
          "medium": 0,
          "hard": 0,
          "deadly": 0,
          "deepFrost": 0,
          "wins": 0,
          "losses": 0
        },
        "competitive": {
          "total": 10,
          "easy": 8,
          "medium": 0,
          "hard": 0,
          "deadly": 2,
          "deepFrost": 0,
          "wins": 8,
          "losses": 2
        },
        "tomesSubmitted": 5,
        "compRuns": 10,
        "pracRuns": 0,
        "totalRuns": 10,
        "compWinRate": 0.8
      }
    ],
    "totalPracRuns": 0,
    "totalCompRuns": 10,
    "totalRunsAllModes": 10
  },
  {
    "player": "werewolf_50",
    "phases": [
      {
        "total": 2,
        "practice": {
          "total": 2,
          "easy": 2,
          "medium": 0,
          "hard": 0,
          "deadly": 0,
          "deepFrost": 0,
          "wins": 0,
          "losses": 2
        },
        "competitive": {
          "total": 0,
          "easy": 0,
          "medium": 0,
          "hard": 0,
          "deadly": 0,
          "deepFrost": 0,
          "wins": 0,
          "losses": 0
        },
        "tomesSubmitted": 0,
        "compRuns": 0,
        "pracRuns": 2,
        "totalRuns": 2,
        "compWinRate": 0
      }
    ],
    "totalPracRuns": 2,
    "totalCompRuns": 0,
    "totalRunsAllModes": 2
  },
  {
    "player": "white_lotussss",
    "phases": [
      {
        "total": 1,
        "practice": {
          "total": 0,
          "easy": 0,
          "medium": 0,
          "hard": 0,
          "deadly": 0,
          "deepFrost": 0,
          "wins": 0,
          "losses": 0
        },
        "competitive": {
          "total": 1,
          "easy": 1,
          "medium": 0,
          "hard": 0,
          "deadly": 0,
          "deepFrost": 0,
          "wins": 0,
          "losses": 1
        },
        "tomesSubmitted": 0,
        "compRuns": 1,
        "pracRuns": 0,
        "totalRuns": 1,
        "compWinRate": 0
      }
    ],
    "totalPracRuns": 0,
    "totalCompRuns": 1,
    "totalRunsAllModes": 1
  }
]
